MainShortcuts/MainCore.py
MainShortcuts/__init__.py
MainShortcuts/addon.py
MainShortcuts/cfg.py
MainShortcuts/dict.py
MainShortcuts/dictplus.py
MainShortcuts/dir.py
MainShortcuts/file.py
MainShortcuts/fileobj.py
MainShortcuts/imports.py
MainShortcuts/json.py
MainShortcuts/list.py
MainShortcuts/main.py
MainShortcuts/os.py
MainShortcuts/path.py
MainShortcuts/proc.py
MainShortcuts/script.py
MainShortcuts/str.py
MainShortcuts/utils.py
MainShortcuts/values.py
MainShortcuts/win.py
mainshortcuts-1.7.4.dist-info/METADATA
mainshortcuts-1.7.4.dist-info/WHEEL
mainshortcuts-1.7.4.dist-info/entry_points.txt
mainshortcuts-1.7.4.dist-info/RECORD
