Metadata-Version: 2.1
Name: MainShortcuts
Version: 1.7.4
Summary: Simplifying Python Built-in Commands
Home-page: https://github.com/MainPlay-TG/MainShortcuts.py
Author: MainPlay TG
Author-email: xbox.roman6666666666@gmail.com
Requires-Python: >=3.7,<4.0
Classifier: Programming Language :: Python :: 3
Classifier: Programming Language :: Python :: 3.7
Classifier: Programming Language :: Python :: 3.8
Classifier: Programming Language :: Python :: 3.9
Classifier: Programming Language :: Python :: 3.10
Classifier: Programming Language :: Python :: 3.11
Classifier: Programming Language :: Python :: 3.12
Project-URL: Repository, https://github.com/MainPlay-TG/MainShortcuts.py
